ppersist/__init__.py
ppersist/ppersist.py
ppersist-0.10.1.dist-info/licenses/LICENSE
tests/test_ppersist.py
ppersist-0.10.1.dist-info/METADATA
ppersist-0.10.1.dist-info/WHEEL
ppersist-0.10.1.dist-info/top_level.txt
ppersist-0.10.1.dist-info/RECORD
