Metadata-Version: 2.4
Name: ppersist
Version: 0.10.1
Summary: Convenient long-term storage of python data
Author-email: Daniel Wagenaar <daw@caltech.edu>
Project-URL: Homepage, https://github.com/wagenadl/ppersist
Classifier: Programming Language :: Python :: 3
Classifier: License :: OSI Approved :: GNU General Public License v3 or later (GPLv3+)
Classifier: Operating System :: OS Independent
Requires-Python: >=3.8
License-File: LICENSE
Requires-Dist: numpy
Requires-Dist: pandas
Dynamic: license-file
